pywander/__init__.py
pywander/cache.py
pywander/common.py
pywander/compat.py
pywander/config.py
pywander/datetime.py
pywander/dict.py
pywander/exceptions.py
pywander/functools.py
pywander/json.py
pywander/list.py
pywander/path.py
pywander/unique_key.py
pywander/web.py
pywander/xml.py
pywander/algorithm/__init__.py
pywander/algorithm/binary_search.py
pywander/algorithm/graph/__init__.py
pywander/algorithm/graph/dag.py
pywander/algorithm/graph/directed_graph.py
pywander/algorithm/graph/exceptions.py
pywander/algorithm/graph/graph.py
pywander/algorithm/graph/undirected_graph.py
pywander/algorithm/graph/weighted_dag.py
pywander/algorithm/problems/__init__.py
pywander/algorithm/problems/hanoi.py
pywander/algorithm/problems/random_walk.py
pywander/algorithm/sort/__init__.py
pywander/algorithm/sort/bubble_sort.py
pywander/algorithm/sort/quick_sort.py
pywander/algorithm/sort/select_sort.py
pywander/algorithm/tree/__init__.py
pywander/algorithm/tree/binary_decision_tree.py
pywander/algorithm/tree/binary_search_tree.py
pywander/algorithm/tree/exceptions.py
pywander/algorithm/tree/tree.py
pywander/crawler/__init__.py
pywander/crawler/js_file_loader.py
pywander/crawler/todo_system.py
pywander/crawler/utils.py
pywander/crawler/web_utils.py
pywander/file/__init__.py
pywander/file/__main__.py
pywander/file/run_py_file.py
pywander/file/scan_file.py
pywander/file/utils.py
pywander/image/__init__.py
pywander/image/__main__.py
pywander/image/convert_image.py
pywander/image/resize_image.py
pywander/image/utils.py
pywander/math/__init__.py
pywander/math/arithmetic.py
pywander/math/calculus.py
pywander/math/excel.py
pywander/math/linear_algebra.py
pywander/utils/__init__.py
pywander/utils/command_utils.py
pywander/utils/df_utils.py
pywander/utils/plot_utils.py
pywander-0.11.1.dist-info/licenses/LICENSE
pywander-0.11.1.dist-info/METADATA
pywander-0.11.1.dist-info/WHEEL
pywander-0.11.1.dist-info/entry_points.txt
pywander-0.11.1.dist-info/top_level.txt
pywander-0.11.1.dist-info/RECORD
