Metadata-Version: 2.4
Name: pywander
Version: 0.11.1
Summary: a general purpose python module.
Home-page: https://github.com/a358003542/pywander
Author: wander
Author-email: a358003542@outlook.com
Maintainer: wander
Maintainer-email: a358003542@outlook.com
License: MIT
Keywords: python
Classifier: Operating System :: Microsoft
Classifier: Operating System :: POSIX :: Linux
Classifier: Programming Language :: Python :: 3
License-File: LICENSE
Requires-Dist: requests
Requires-Dist: python-dateutil
Requires-Dist: click
Requires-Dist: pillow>=10.0.0
Requires-Dist: numpy
Requires-Dist: matplotlib
Requires-Dist: my_fake_useragent
Requires-Dist: diskcache
Requires-Dist: pyparsing
Requires-Dist: lxml
Requires-Dist: pandas
Dynamic: license-file
